st_track_analysis/__init__.py
st_track_analysis/frontend/build/asset-manifest.json
st_track_analysis/frontend/build/index.html
st_track_analysis/frontend/build/static/css/main.885a9fab.chunk.css
st_track_analysis/frontend/build/static/css/main.885a9fab.chunk.css.map
st_track_analysis/frontend/build/static/js/2.44f13161.chunk.js
st_track_analysis/frontend/build/static/js/2.44f13161.chunk.js.LICENSE.txt
st_track_analysis/frontend/build/static/js/2.44f13161.chunk.js.map
st_track_analysis/frontend/build/static/js/main.e97d1cd0.chunk.js
st_track_analysis/frontend/build/static/js/main.e97d1cd0.chunk.js.map
st_track_analysis/frontend/build/static/js/runtime-main.39defc4e.js
st_track_analysis/frontend/build/static/js/runtime-main.39defc4e.js.map
st_track_analysis-0.0.7.dist-info/LICENSE
st_track_analysis-0.0.7.dist-info/METADATA
st_track_analysis-0.0.7.dist-info/WHEEL
st_track_analysis-0.0.7.dist-info/top_level.txt
st_track_analysis-0.0.7.dist-info/RECORD
