Metadata-Version: 2.1
Name: st-track-analysis
Version: 0.0.7
Summary: A Streamlit component for visualizing track data on images
Home-page: 
Author: Elliot Glas
Author-email: elliot.glas@viscando.com
Requires-Python: >=3.6
License-File: LICENSE
Requires-Dist: streamlit (>=0.63)
